rsm/__init__.py
rsm/__main__.py
rsm/redis-commands.txt
rsm/monkey_patch/__init__.py
rsm/monkey_patch/aioredis.py
rsm/monkey_patch/pyredis.py
redis_security_mapper-0.0.5.dist-info/LICENSE
redis_security_mapper-0.0.5.dist-info/METADATA
redis_security_mapper-0.0.5.dist-info/WHEEL
redis_security_mapper-0.0.5.dist-info/entry_points.txt
redis_security_mapper-0.0.5.dist-info/top_level.txt
redis_security_mapper-0.0.5.dist-info/zip-safe
redis_security_mapper-0.0.5.dist-info/RECORD
