Metadata-Version: 2.1
Name: redis-security-mapper
Version: 0.0.5
Summary: hide redis server command to attackers
Home-page: https://github.com/cr0hn/rsm
License: License :: OSI Approved :: BSD License
Platform: UNKNOWN
Classifier: Programming Language :: Python :: 3.8
Requires-Python: >=3.8
